monocle_social_buttons-0.2.0.3.dist-info/metadata.json
monocle_social_buttons-0.2.0.3.dist-info/WHEEL
monocle_social_buttons-0.2.0.3.dist-info/METADATA
monocle_social_buttons-0.2.0.3.dist-info/top_level.txt
monocle_social_buttons-0.2.0.3.dist-info/DESCRIPTION.rst
monocle_social_buttons-0.2.0.3.dist-info/RECORD
monocle_social_buttons/__init__.py
monocle_social_buttons/models.py
monocle_social_buttons/monocle.py
monocle_social_buttons/admin.py
monocle_social_buttons/templates/monocle_social_buttons/monocle_social_buttons.html
monocle_social_buttons/fixtures/monocle_social_buttons.json
monocle_social_buttons/fixtures/monocle_social_buttons/twitter_logo.png
monocle_social_buttons/fixtures/monocle_social_buttons/vkontakte_logo.png
monocle_social_buttons/fixtures/monocle_social_buttons/facebook_logo.png
monocle_social_buttons/fixtures/monocle_social_buttons/Tulips.jpg
monocle_social_buttons/fixtures/monocle_social_buttons/linkedIn_logo.png
monocle_social_buttons/static/monocle_social_buttons/monocle_social_buttons.css
