Metadata-Version: 2.0
Name: monocle-social-buttons
Version: 0.2.0.3
Summary: Social buttons for landings
Home-page: UNKNOWN
Author: Alexander Kalinin @Langprism LTD
Author-email: ak@langprism.com
License: BSD License
Platform: UNKNOWN
Classifier: Environment :: Web Environment
Classifier: Framework :: Django
Classifier: Intended Audience :: Developers
Classifier: License :: OSI Approved :: BSD License
Classifier: Operating System :: OS Independent
Classifier: Programming Language :: Python
Classifier: Programming Language :: Python :: 3
Classifier: Programming Language :: Python :: 3.2
Classifier: Programming Language :: Python :: 3.3
Classifier: Topic :: Internet :: WWW/HTTP
Classifier: Topic :: Internet :: WWW/HTTP :: Dynamic Content
Requires-Dist: pillow
Requires-Dist: easy-thumbnails
